spimcube/__init__.py
spimcube/functions.py
spimcube/procedures.py
spimcube/spimclass.py
spimcube/utils.py
spimcube-1.5.3.dist-info/LICENSE
spimcube-1.5.3.dist-info/METADATA
spimcube-1.5.3.dist-info/WHEEL
spimcube-1.5.3.dist-info/top_level.txt
spimcube-1.5.3.dist-info/RECORD
