Metadata-Version: 2.1
Name: spimcube
Version: 1.5.3
Summary: This package enables the exploration of datacube of spectra within a GUI interface built on matplotlib and brings a handful of function tools.
Home-page: https://github.com/Tom-P7/spimcube
Author: Thomas Pelini
Author-email: thomas.pelini@orange.fr
License: MIT
Keywords: spim,datacube,hyperspectral, 3D map
Platform: UNKNOWN
Classifier: Programming Language :: Python :: 3
Classifier: License :: OSI Approved :: MIT License
Classifier: Operating System :: OS Independent
Requires-Python: >=3.6
License-File: LICENSE
Requires-Dist: matplotlib (>=3.1)
Requires-Dist: numpy
Requires-Dist: scipy
Requires-Dist: pandas
Requires-Dist: colorcet
Requires-Dist: despike
Requires-Dist: lmfit
